indago/__init__.py
indago/_abc.py
indago/_ba.py
indago/_bo.py
indago/_cmaes.py
indago/_de.py
indago/_eeeo.py
indago/_efo.py
indago/_esc.py
indago/_fwa.py
indago/_gd.py
indago/_gwo.py
indago/_mrfo.py
indago/_msgd.py
indago/_nm.py
indago/_optimizer.py
indago/_pso.py
indago/_rbs.py
indago/_rs.py
indago/_sa.py
indago/_ssa.py
indago/_utility.py
indagobench/optimizers/__init__.py
indagobench/optimizers/_optimizers_nlopt.py
indagobench/optimizers/_optimizers_pymoo.py
indagobench/optimizers/_optimizers_scipy.py
indagobench/optimizers/_optimizers_zoopt.py
indagobench/optimizers/_standard_test_optimizers.py
indagobench/postprocessing/__init__.py
indagobench/postprocessing/check_for_nonuniqe_results.py
indagobench/postprocessing/check_results.py
indagobench/postprocessing/clean_files.py
indagobench/postprocessing/convert_raw_results_to_new_format.py
indagobench/postprocessing/create_convergence_plots.py
indagobench/postprocessing/create_summaries.py
indagobench/postprocessing/optimizer_radar_plots.py
indagobench/postprocessing/post_analysis.py
indagobench/postprocessing/rename_optimizer.py
indagobench/postprocessing/svd_analysis.py
indagobench/problems/__init__.py
indagobench/problems/_airfoil_design.py
indagobench/problems/_analytical_engineering_problems.py
indagobench/problems/_cec2014.py
indagobench/problems/_empirical_regression.py
indagobench/problems/_ergodic.py
indagobench/problems/_flow_fit.py
indagobench/problems/_hydraulic_network.py
indagobench/problems/_ill_posed_problems.py
indagobench/problems/_indagobench25_problems.py
indagobench/problems/_packing_problems.py
indagobench/problems/_shortest_path.py
indagobench/problems/_structural_frame.py
indagobench/problems/hydraulic_network_data/__init__.py
indagobench/problems/hydraulic_network_data/try_network.py
indagobench/problems/shortest_path_data/__init__.py
indagobench/problems/shortest_path_data/change.py
indago-0.5.4.dist-info/METADATA
indago-0.5.4.dist-info/WHEEL
indago-0.5.4.dist-info/top_level.txt
indago-0.5.4.dist-info/RECORD
