Metadata-Version: 2.4
Name: Indago
Version: 0.5.4
Summary: Numerical optimization framework
Author: Department of fluid mechanics and computational engineering, Faculty of engineering, University of Rijeka
Author-email: stefan.ivic@uniri.hr
Project-URL: Documentation, https://indago.readthedocs.io/
Project-URL: GitLab, https://gitlab.com/sivic/indago
Classifier: Programming Language :: Python :: 3
Classifier: License :: OSI Approved :: MIT License
Classifier: Operating System :: OS Independent
Requires-Python: >=3.9
Requires-Dist: numpy>=1.22.2
Requires-Dist: matplotlib>=3.6
Requires-Dist: scipy>=1.6.3
Requires-Dist: rich>=12.5
Dynamic: author
Dynamic: author-email
Dynamic: classifier
Dynamic: description
Dynamic: description-content-type
Dynamic: project-url
Dynamic: requires-dist
Dynamic: requires-python
Dynamic: summary
